xeasy_ml/__init__.py
xeasy_ml/project_init/create_demo.conf
xeasy_ml/project_init/create_new_demo.py
xeasy_ml/project_init/project_init.md
xeasy_ml/xes_ml_arch/__init__.py
xeasy_ml/xes_ml_arch/__main__.py
xeasy_ml/xes_ml_arch/config/log.conf
xeasy_ml/xes_ml_arch/config/demo/analysis.conf
xeasy_ml/xes_ml_arch/config/demo/cross_validation.conf
xeasy_ml/xes_ml_arch/config/demo/data_split.conf
xeasy_ml/xes_ml_arch/config/demo/feature_enginnering.conf
xeasy_ml/xes_ml_arch/config/demo/ml.conf
xeasy_ml/xes_ml_arch/config/demo/model.conf
xeasy_ml/xes_ml_arch/data/sample.txt
xeasy_ml/xes_ml_arch/log/access.log
xeasy_ml/xes_ml_arch/result/test.txt
xeasy_ml/xes_ml_arch/src/__init__.py
xeasy_ml/xes_ml_arch/src/analysis/__init__.py
xeasy_ml/xes_ml_arch/src/analysis/analysis.py
xeasy_ml/xes_ml_arch/src/constance/__init__.py
xeasy_ml/xes_ml_arch/src/constance/predict_constance.py
xeasy_ml/xes_ml_arch/src/cross_validation/__init__.py
xeasy_ml/xes_ml_arch/src/cross_validation/cross_validation.py
xeasy_ml/xes_ml_arch/src/cross_validation/data_split.py
xeasy_ml/xes_ml_arch/src/feature_enginnering/__init__.py
xeasy_ml/xes_ml_arch/src/feature_enginnering/data_processor.py
xeasy_ml/xes_ml_arch/src/feature_enginnering/data_sampler.py
xeasy_ml/xes_ml_arch/src/feature_enginnering/data_washer.py
xeasy_ml/xes_ml_arch/src/feature_enginnering/feature_discretizer.py
xeasy_ml/xes_ml_arch/src/feature_enginnering/feature_filter.py
xeasy_ml/xes_ml_arch/src/feature_enginnering/pre_feature_utils.py
xeasy_ml/xes_ml_arch/src/feature_enginnering/xes_onehot_encoder.py
xeasy_ml/xes_ml_arch/src/ml/__init__.py
xeasy_ml/xes_ml_arch/src/ml/base_ml.py
xeasy_ml/xes_ml_arch/src/ml/prediction_ml.py
xeasy_ml/xes_ml_arch/src/ml/train_model_ml.py
xeasy_ml/xes_ml_arch/src/ml_utils/__init__.py
xeasy_ml/xes_ml_arch/src/ml_utils/configmanager.py
xeasy_ml/xes_ml_arch/src/ml_utils/feature_processor.py
xeasy_ml/xes_ml_arch/src/ml_utils/global_pre.py
xeasy_ml/xes_ml_arch/src/ml_utils/jsonmanager.py
xeasy_ml-0.1.3.dist-info/LICENSE
xeasy_ml-0.1.3.dist-info/METADATA
xeasy_ml-0.1.3.dist-info/WHEEL
xeasy_ml-0.1.3.dist-info/top_level.txt
xeasy_ml-0.1.3.dist-info/RECORD
