Metadata-Version: 2.1
Name: xeasy-ml
Version: 0.1.3
Summary: An integrated machine learning analysis framework
Home-page: UNKNOWN
Author: X
Author-email: author@example.com
License: UNKNOWN
Platform: UNKNOWN
Classifier: Programming Language :: Python :: 3
Classifier: License :: OSI Approved :: MIT License
Classifier: Operating System :: OS Independent
Requires-Python: >=3.6
License-File: LICENSE
Requires-Dist: scikit-learn (==0.24.1)
Requires-Dist: pandas (==0.24.2)
Requires-Dist: matplotlib (==3.3.4)
Requires-Dist: pydotplus (==2.0.2)
Requires-Dist: xgboost (==1.4.2)
Requires-Dist: numpy (==1.19.5)
